cmdint/CmdInterface.py
cmdint/MessageLogger.py
cmdint/Utils.py
cmdint/__init__.py
cmdint-3.0.6.dist-info/LICENSE
cmdint-3.0.6.dist-info/METADATA
cmdint-3.0.6.dist-info/WHEEL
cmdint-3.0.6.dist-info/top_level.txt
cmdint-3.0.6.dist-info/RECORD
