Metadata-Version: 2.1
Name: cmdint
Version: 3.0.6
Summary: Enables detailed logging of command line calls in a very lightweight manner.
Home-page: https://github.com/MIC-DKFZ/cmdint/
Author: Peter F. Neher
Author-email: p.neher@dkfz.de
License: Apache 2.0
Platform: UNKNOWN
Classifier: Programming Language :: Python :: 3
Classifier: Operating System :: OS Independent
Classifier: Development Status :: 5 - Production/Stable
License-File: LICENSE
Requires-Dist: GitPython
Requires-Dist: chardet
Requires-Dist: psutil
Requires-Dist: python-telegram-bot
Requires-Dist: slackclient
Requires-Dist: xmltodict
